Metadata-Version: 2.1
Name: minicapy
Version: 1.1.2
Summary: Minica python lib
Home-page: https://github.com/bjornsnoen/minicapy
Maintainer: Bjørn Snoen
Maintainer-email: bjorn.snoen+minica@gmail.com
License: GPLv3
Platform: linux-x86_64
Requires-Python: >=3.7
License-File: LICENSE.md
